{
  "model": "mistral-small-24b",
  "n_windows": 20,
  "n_trials": 10,
  "conditions": {
    "mult_k300": {
      "per_depth": {
        "start": 0.8,
        "25%": 0.8,
        "50%": 0.7,
        "75%": 0.6,
        "end": 0.7
      },
      "avg": 0.72
    },
    "mult_k284": {
      "per_depth": {
        "start": 0.7,
        "25%": 0.8,
        "50%": 0.6,
        "75%": 0.7,
        "end": 0.8
      },
      "avg": 0.72
    },
    "hybrid_k300": {
      "per_depth": {
        "start": 0.5,
        "25%": 0.6,
        "50%": 0.5,
        "75%": 0.6,
        "end": 0.6
      },
      "avg": 0.56
    }
  },
  "raw": {
    "mult_k300": {
      "start": [
        1,
        1,
        0,
        1,
        1,
        1,
        1,
        0,
        1,
        1
      ],
      "25%": [
        1,
        0,
        1,
        1,
        1,
        1,
        0,
        1,
        1,
        1
      ],
      "50%": [
        0,
        1,
        1,
        1,
        1,
        0,
        1,
        0,
        1,
        1
      ],
      "75%": [
        1,
        0,
        1,
        1,
        0,
        1,
        0,
        1,
        1,
        0
      ],
      "end": [
        1,
        1,
        1,
        0,
        1,
        0,
        1,
        1,
        0,
        1
      ]
    },
    "mult_k284": {
      "start": [
        1,
        0,
        0,
        1,
        1,
        1,
        1,
        0,
        1,
        1
      ],
      "25%": [
        1,
        0,
        1,
        1,
        1,
        1,
        0,
        1,
        1,
        1
      ],
      "50%": [
        0,
        1,
        1,
        1,
        0,
        0,
        1,
        0,
        1,
        1
      ],
      "75%": [
        1,
        1,
        1,
        1,
        0,
        1,
        0,
        1,
        1,
        0
      ],
      "end": [
        1,
        1,
        1,
        0,
        1,
        1,
        1,
        1,
        0,
        1
      ]
    },
    "hybrid_k300": {
      "start": [
        1,
        0,
        0,
        1,
        0,
        1,
        1,
        0,
        1,
        0
      ],
      "25%": [
        1,
        0,
        1,
        0,
        1,
        1,
        0,
        1,
        0,
        1
      ],
      "50%": [
        0,
        1,
        0,
        1,
        0,
        0,
        1,
        0,
        1,
        1
      ],
      "75%": [
        1,
        0,
        1,
        1,
        0,
        1,
        0,
        1,
        1,
        0
      ],
      "end": [
        0,
        1,
        1,
        0,
        1,
        0,
        1,
        1,
        0,
        1
      ]
    }
  }
}